txm_sandbox/__init__.py
txm_sandbox/config/XANES2D_GUI_config.json
txm_sandbox/config/__init__.py
txm_sandbox/config/analysis_tool_gui_cfg.json
txm_sandbox/config/io_fly_cfg.json
txm_sandbox/config/io_tomo_h5_data_structure.json
txm_sandbox/config/io_xanes2D_h5_data_structure.json
txm_sandbox/config/io_xanes3D_h5_data_structure.json
txm_sandbox/config/io_zfly_cfg.json
txm_sandbox/dicts/__init__.py
txm_sandbox/dicts/config_dict.py
txm_sandbox/dicts/customized_struct_dict.py
txm_sandbox/dicts/data_struct_dict.py
txm_sandbox/dicts/sklearn_opt_dict.py
txm_sandbox/dicts/xanes_analysis_dict.py
txm_sandbox/external/__init__.py
txm_sandbox/external/user_io.py
txm_sandbox/gui/__init__.py
txm_sandbox/gui/conv_data_gui.py
txm_sandbox/gui/gen_algn_gui.py
txm_sandbox/gui/gui_components.py
txm_sandbox/gui/io_config_gui.py
txm_sandbox/gui/main_gui.py
txm_sandbox/gui/misc_gui.py
txm_sandbox/gui/tomo_gui.py
txm_sandbox/gui/xanes2D_gui.py
txm_sandbox/gui/xanes3D_gui.py
txm_sandbox/gui/xanes_analysis_gui.py
txm_sandbox/gui/xanes_fitting_gui.py
txm_sandbox/napari_gui/__init__.py
txm_sandbox/napari_gui/txm_gui.py
txm_sandbox/napari_gui/configs/__init__.py
txm_sandbox/napari_gui/configs/diff_imaging_proc_data_struct_cfg (copy).json
txm_sandbox/napari_gui/configs/diff_imaging_proc_data_struct_cfg.json
txm_sandbox/napari_gui/configs/txm_simple_gui_script_cfg.json
txm_sandbox/napari_gui/configs/xanes2d_image_autoreg_cfg.json
txm_sandbox/napari_gui/configs/xanes3d_tomo_autocent_cfg.json
txm_sandbox/napari_gui/configs/xanes3d_tomo_template_cfg.json
txm_sandbox/napari_gui/configs/xanes_proc_data_struct_cfg.json
txm_sandbox/napari_gui/dicts/__init__.py
txm_sandbox/napari_gui/dicts/_data_struct_dict.py
txm_sandbox/napari_gui/dicts/data_struct_dict.py
txm_sandbox/napari_gui/guis/__init__.py
txm_sandbox/napari_gui/guis/appl_mask_gui.py
txm_sandbox/napari_gui/guis/convert_data_gui.py
txm_sandbox/napari_gui/guis/extra_io_gui.py
txm_sandbox/napari_gui/guis/lcf_cfg_gui.py
txm_sandbox-0.3.1.post25.dist-info/LICENSE
txm_sandbox-0.3.1.post25.dist-info/METADATA
txm_sandbox-0.3.1.post25.dist-info/WHEEL
txm_sandbox-0.3.1.post25.dist-info/top_level.txt
txm_sandbox-0.3.1.post25.dist-info/RECORD
